src/__init__.py
iiii-0.1.1.dist-info/LICENSE
iiii-0.1.1.dist-info/METADATA
iiii-0.1.1.dist-info/WHEEL
iiii-0.1.1.dist-info/top_level.txt
iiii-0.1.1.dist-info/RECORD
