Metadata-Version: 2.1
Name: iiii
Version: 0.1.1
Summary: iiii [Four Eyes], a search engine that helps you look wider and deeper
Home-page: https://github.com/dmgolembiowski/iiii
Author: David M. Golembiowski
Author-email: dmgolembiowski@gmail.com
License: UNKNOWN
Platform: UNKNOWN
Classifier: Programming Language :: Python :: 3
Classifier: License :: OSI Approved :: MIT License
Classifier: Operating System :: OS Independent
Requires-Python: >=3.7
